{"assets":{"598D726EDE84BC1689DB052B83637AB0":{"type":"texture","index":14,"assetRequest":{"type":"slide","state":"contents","slide":"none"},"url":{"native":"assets\/4A9C89DE-0728-4606-BE7F-0A540FE354A2.pdf"},"width":302,"height":57},"3FC21BC9DAF17E097D2300B1C642C405":{"type":"texture","index":0,"assetRequest":{"type":"slide","state":"contents","slide":"none"},"url":{"native":"assets\/4A9C89DE-0728-4606-BE7F-0A540FE354A2.pdf"},"width":1920,"height":1080},"92685EF305F612428C44D7A698BF32EC":{"type":"texture","index":17,"assetRequest":{"type":"slide","state":"contents","slide":"none"},"url":{"native":"assets\/4A9C89DE-0728-4606-BE7F-0A540FE354A2.pdf"},"width":619,"height":50},"678B3409415B9811738E10E21988BFEB":{"type":"texture","index":16,"assetRequest":{"type":"slide","state":"contents","slide":"none"},"url":{"native":"assets\/4A9C89DE-0728-4606-BE7F-0A540FE354A2.pdf"},"width":431,"height":50},"70D46D016A3FCA36FDE43DAB46DE49AD":{"type":"texture","index":11,"assetRequest":{"type":"slide","state":"contents","slide":"none"},"url":{"native":"assets\/4A9C89DE-0728-4606-BE7F-0A540FE354A2.pdf"},"width":457,"height":50},"689124FC3E296698DE64C81C316E84BD":{"type":"texture","index":7,"assetRequest":{"type":"slide","state":"contents","slide":"none"},"url":{"native":"assets\/4A9C89DE-0728-4606-BE7F-0A540FE354A2.pdf"},"width":369,"height":49},"836EA704896FC529AF870C42E7EF2500":{"type":"texture","index":12,"assetRequest":{"type":"slide","state":"contents","slide":"none"},"url":{"native":"assets\/4A9C89DE-0728-4606-BE7F-0A540FE354A2.pdf"},"width":465,"height":50},"D9675965E73A9FBE25A5CF025DA70F5D":{"type":"texture","index":10,"assetRequest":{"type":"slide","state":"contents","slide":"none"},"url":{"native":"assets\/4A9C89DE-0728-4606-BE7F-0A540FE354A2.pdf"},"width":495,"height":49},"95BBD3B069FF32CAA2226F972BE9CC09":{"type":"texture","index":18,"assetRequest":{"type":"slide","state":"contents","slide":"none"},"url":{"native":"assets\/4A9C89DE-0728-4606-BE7F-0A540FE354A2.pdf"},"width":462,"height":474},"EA78131353955516F02AF418FDBFC37F":{"type":"texture","index":15,"assetRequest":{"type":"slide","state":"contents","slide":"none"},"url":{"native":"assets\/4A9C89DE-0728-4606-BE7F-0A540FE354A2.pdf"},"width":274,"height":50},"AA7AF5330EFB1B04DADB648822DA59DD":{"type":"texture","index":4,"assetRequest":{"type":"slide","state":"contents","slide":"none"},"url":{"native":"assets\/4A9C89DE-0728-4606-BE7F-0A540FE354A2.pdf"},"width":456,"height":50},"3AB81D1FC31F83B945888240D4239869":{"type":"texture","index":3,"assetRequest":{"type":"slide","state":"contents","slide":"none"},"url":{"native":"assets\/4A9C89DE-0728-4606-BE7F-0A540FE354A2.pdf"},"width":414,"height":50},"903EA47FD208B72A1097F1E473D61AAA":{"type":"texture","index":9,"assetRequest":{"type":"slide","state":"contents","slide":"none"},"url":{"native":"assets\/4A9C89DE-0728-4606-BE7F-0A540FE354A2.pdf"},"width":326,"height":50},"2B389D0EE43EBB4A844CF8214803FA66":{"type":"texture","index":8,"assetRequest":{"type":"slide","state":"contents","slide":"none"},"url":{"native":"assets\/4A9C89DE-0728-4606-BE7F-0A540FE354A2.pdf"},"width":282,"height":49},"20971E7F33692F6B8FCD8DBF7F8B5D0E":{"type":"texture","index":1,"assetRequest":{"type":"slide","state":"contents","slide":"none"},"url":{"native":"assets\/4A9C89DE-0728-4606-BE7F-0A540FE354A2.pdf"},"width":885,"height":76},"02DA42B8BBA00178F5E0C7A57CF788DE":{"type":"texture","index":2,"assetRequest":{"type":"slide","state":"contents","slide":"none"},"url":{"native":"assets\/4A9C89DE-0728-4606-BE7F-0A540FE354A2.pdf"},"width":554,"height":50},"12ECBE31370EBED8AC47C416E4745FC5":{"type":"texture","index":13,"assetRequest":{"type":"slide","state":"contents","slide":"none"},"url":{"native":"assets\/4A9C89DE-0728-4606-BE7F-0A540FE354A2.pdf"},"width":274,"height":50},"0039962803FEF133B7DAD23E95B3B04F":{"type":"texture","index":5,"assetRequest":{"type":"slide","state":"contents","slide":"none"},"url":{"native":"assets\/4A9C89DE-0728-4606-BE7F-0A540FE354A2.pdf"},"width":571,"height":60},"819791604C975CE9051B049C6D72FEE9":{"type":"texture","index":6,"assetRequest":{"type":"slide","state":"contents","slide":"none"},"url":{"native":"assets\/4A9C89DE-0728-4606-BE7F-0A540FE354A2.pdf"},"width":434,"height":49}},"events":[{"effects":[{"beginTime":0,"baseLayer":{"animations":[],"initialState":{"affineTransform":[1,0,0,1,0,0],"masksToBounds":false,"rotation":0,"scale":1,"position":{"pointX":960,"pointY":540},"width":1920,"sublayerTransform":[1,0,0,0,0,1,0,0,0,0,1,0,0,0,0,1],"contentsRect":{"y":0,"x":0,"width":1,"height":1},"opacity":1,"edgeAntialiasingMask":251658240,"height":1080,"hidden":false,"anchorPoint":{"pointX":0.5,"pointY":0.5}},"objectID":"0","layers":[{"animations":[],"initialState":{"affineTransform":[1,0,0,1,0,0],"masksToBounds":false,"rotation":0,"scale":1,"position":{"pointX":960,"pointY":540},"width":1920,"sublayerTransform":[1,0,0,0,0,1,0,0,0,0,1,-0.00035007912466775983,0,0,0,1],"contentsRect":{"y":0,"x":0,"width":1,"height":1},"opacity":1,"edgeAntialiasingMask":251658240,"height":1080,"hidden":false,"anchorPoint":{"pointX":0.5,"pointY":0.5}},"layers":[{"animations":[{"additive":false,"timeOffset":0,"beginTime":0,"repeatCount":0,"fillMode":"both","duration":1.25,"autoreverses":false,"animations":[{"repeatCount":0,"removedOnCompletion":true,"from":{"scalar":0},"timingFunction":"EaseInEaseOut","additive":false,"timeOffset":0,"autoreverses":false,"property":"zPosition","fillMode":"both","duration":1.25,"beginTime":0,"to":{"scalar":0}}],"removedOnCompletion":false}],"initialState":{"affineTransform":[1,0,0,1,0,0],"masksToBounds":false,"rotation":0,"scale":1,"position":{"pointX":960,"pointY":540},"width":1920,"sublayerTransform":[1,0,0,0,0,1,0,0,0,0,1,0,0,0,0,1],"contentsRect":{"y":0,"x":0,"width":1,"height":1},"opacity":1,"edgeAntialiasingMask":251658240,"height":1080,"hidden":false,"anchorPoint":{"pointX":0.5,"pointY":0.5}},"layers":[{"animations":[],"layers":[],"texturedRectangle":{"isBackgroundTexture":true,"singleTextureOpacity":1,"textureType":1,"textBaseline":0,"textXHeight":0,"isVerticalText":false},"initialState":{"affineTransform":[1,0,0,1,0,0],"masksToBounds":false,"rotation":0,"scale":1,"position":{"pointX":960,"pointY":540},"width":1920,"sublayerTransform":[1,0,0,0,0,1,0,0,0,0,1,0,0,0,0,1],"contentsRect":{"y":0,"x":0,"width":1,"height":1},"opacity":1,"edgeAntialiasingMask":0,"height":1080,"hidden":false,"anchorPoint":{"pointX":0.5,"pointY":0.5}},"texture":"3FC21BC9DAF17E097D2300B1C642C405"}]}]},{"animations":[{"additive":false,"timeOffset":0,"beginTime":0,"repeatCount":0,"fillMode":"both","duration":1.25,"autoreverses":false,"animations":[{"repeatCount":0,"removedOnCompletion":true,"from":{"scalar":0.001},"timingFunction":"EaseInEaseOut","additive":false,"timeOffset":0,"autoreverses":false,"property":"zPosition","fillMode":"both","duration":1.25,"beginTime":0,"to":{"scalar":0.001}}],"removedOnCompletion":false}],"initialState":{"affineTransform":[1,0,0,1,0,0],"masksToBounds":false,"rotation":0,"scale":1,"position":{"pointX":576.22085571289062,"pointY":127.45227813720703},"width":962.44195556640625,"sublayerTransform":[1,0,0,0,0,1,0,0,0,0,1,0,0,0,0,1],"contentsRect":{"y":0,"x":0,"width":1,"height":1},"opacity":1,"edgeAntialiasingMask":251658240,"height":130.80320739746094,"hidden":false,"anchorPoint":{"pointX":0.5,"pointY":0.5}},"layers":[{"animations":[{"additive":false,"timeOffset":0,"beginTime":0,"repeatCount":0,"fillMode":"both","duration":1.25,"autoreverses":false,"animations":[{"repeatCount":0,"removedOnCompletion":true,"from":{"texture":"20971E7F33692F6B8FCD8DBF7F8B5D0E"},"timingFunction":"EaseInEaseOut","additive":false,"timeOffset":0,"autoreverses":false,"property":"contents","fillMode":"both","duration":1.25,"beginTime":0,"to":{"texture":"20971E7F33692F6B8FCD8DBF7F8B5D0E"}}],"removedOnCompletion":false}],"layers":[],"texturedRectangle":{"singleTextureOpacity":1,"textXHeight":0.63998684210526324,"textBaseline":0.95606093540003423,"isBackgroundTexture":true,"isVerticalText":false,"textColor":[1,1,1,1],"textureType":6},"initialState":{"affineTransform":[1,0,0,1,0,0],"masksToBounds":false,"rotation":0,"scale":1,"position":{"pointX":481.22097778320312,"pointY":65.401603698730469},"width":885,"sublayerTransform":[1,0,0,0,0,1,0,0,0,0,1,0,0,0,0,1],"contentsRect":{"y":0,"x":0,"width":1,"height":1},"opacity":1,"edgeAntialiasingMask":0,"height":76,"hidden":false,"anchorPoint":{"pointX":0.53923260532530015,"pointY":0.41384576496325043}},"texture":"20971E7F33692F6B8FCD8DBF7F8B5D0E"}]},{"animations":[{"additive":false,"timeOffset":0,"beginTime":0,"repeatCount":0,"fillMode":"both","duration":1.25,"autoreverses":false,"animations":[{"repeatCount":0,"removedOnCompletion":true,"from":{"scalar":0.002},"timingFunction":"EaseInEaseOut","additive":false,"timeOffset":0,"autoreverses":false,"property":"zPosition","fillMode":"both","duration":1.25,"beginTime":0,"to":{"scalar":0.002}}],"removedOnCompletion":false}],"initialState":{"affineTransform":[1,0,0,1,0,0],"masksToBounds":false,"rotation":0,"scale":1,"position":{"pointX":507.48440933227539,"pointY":628.621826171875},"width":809.47780609130859,"sublayerTransform":[1,0,0,0,0,1,0,0,0,0,1,0,0,0,0,1],"contentsRect":{"y":0,"x":0,"width":1,"height":1},"opacity":1,"edgeAntialiasingMask":251658240,"height":567.39997863769531,"hidden":false,"anchorPoint":{"pointX":0.5,"pointY":0.5}},"layers":[{"animations":[{"additive":false,"timeOffset":0,"beginTime":0,"repeatCount":0,"fillMode":"both","duration":1.25,"autoreverses":false,"animations":[{"repeatCount":0,"removedOnCompletion":true,"from":{"scalar":1},"timingFunction":"EaseInEaseOut","additive":false,"timeOffset":0,"autoreverses":false,"property":"opacity","fillMode":"forwards","duration":0.41662499999999997,"beginTime":0,"to":{"scalar":0}},{"additive":false,"timeOffset":0,"beginTime":0.41662499999999997,"from":{"scalar":true},"repeatCount":0,"fillMode":"forwards","duration":0.83337499999999998,"autoreverses":false,"property":"hidden","to":{"scalar":true},"removedOnCompletion":true}],"removedOnCompletion":false}],"layers":[],"texturedRectangle":{"singleTextureOpacity":1,"textXHeight":0.62759999999999994,"textBaseline":0.96243617773056034,"isBackgroundTexture":true,"isVerticalText":false,"textColor":[0.99991613626480103,1,0.99988490343093872,1],"textureType":6},"initialState":{"affineTransform":[1,0,0,1,0,0],"masksToBounds":false,"rotation":0,"scale":1,"position":{"pointX":404.73892211914062,"pointY":283.69999939203262},"width":554,"sublayerTransform":[1,0,0,0,0,1,0,0,0,0,1,0,0,0,0,1],"contentsRect":{"y":0,"x":0,"width":1,"height":1},"opacity":1,"edgeAntialiasingMask":0,"height":50,"hidden":false,"anchorPoint":{"pointX":0.69582026788043627,"pointY":5.2324367249011994}},"texture":"02DA42B8BBA00178F5E0C7A57CF788DE"}]},{"animations":[{"additive":false,"timeOffset":0,"beginTime":0,"repeatCount":0,"fillMode":"both","duration":1.25,"autoreverses":false,"animations":[{"repeatCount":0,"removedOnCompletion":true,"from":{"scalar":0.0030000000000000001},"timingFunction":"EaseInEaseOut","additive":false,"timeOffset":0,"autoreverses":false,"property":"zPosition","fillMode":"both","duration":1.25,"beginTime":0,"to":{"scalar":0.0030000000000000001}}],"removedOnCompletion":false}],"initialState":{"affineTransform":[1,0,0,1,0,0],"masksToBounds":false,"rotation":0,"scale":1,"position":{"pointX":507.48440933227539,"pointY":628.621826171875},"width":809.47780609130859,"sublayerTransform":[1,0,0,0,0,1,0,0,0,0,1,0,0,0,0,1],"contentsRect":{"y":0,"x":0,"width":1,"height":1},"opacity":1,"edgeAntialiasingMask":251658240,"height":567.39997863769531,"hidden":false,"anchorPoint":{"pointX":0.5,"pointY":0.5}},"layers":[{"animations":[{"additive":false,"timeOffset":0,"beginTime":0,"repeatCount":0,"fillMode":"both","duration":1.25,"autoreverses":false,"animations":[{"repeatCount":0,"removedOnCompletion":true,"from":{"scalar":1},"timingFunction":"EaseInEaseOut","additive":false,"timeOffset":0,"autoreverses":false,"property":"opacity","fillMode":"forwards","duration":0.41662499999999997,"beginTime":0,"to":{"scalar":0}},{"additive":false,"timeOffset":0,"beginTime":0.41662499999999997,"from":{"scalar":true},"repeatCount":0,"fillMode":"forwards","duration":0.83337499999999998,"autoreverses":false,"property":"hidden","to":{"scalar":true},"removedOnCompletion":true}],"removedOnCompletion":false}],"layers":[],"texturedRectangle":{"singleTextureOpacity":1,"textXHeight":0.62759999999999994,"textBaseline":0.96243617773056034,"isBackgroundTexture":true,"isVerticalText":false,"textColor":[0.99991613626480103,1,0.99988490343093872,1],"textureType":6},"initialState":{"affineTransform":[1,0,0,1,0,0],"masksToBounds":false,"rotation":0,"scale":1,"position":{"pointX":404.73892211914062,"pointY":283.69999939203262},"width":414,"sublayerTransform":[1,0,0,0,0,1,0,0,0,0,1,0,0,0,0,1],"contentsRect":{"y":0,"x":0,"width":1,"height":1},"opacity":1,"edgeAntialiasingMask":0,"height":50,"hidden":false,"anchorPoint":{"pointX":0.93112180774338582,"pointY":2.0324367249011992}},"texture":"3AB81D1FC31F83B945888240D4239869"}]},{"animations":[{"additive":false,"timeOffset":0,"beginTime":0,"repeatCount":0,"fillMode":"both","duration":1.25,"autoreverses":false,"animations":[{"repeatCount":0,"removedOnCompletion":true,"from":{"scalar":0.0040000000000000001},"timingFunction":"EaseInEaseOut","additive":false,"timeOffset":0,"autoreverses":false,"property":"zPosition","fillMode":"both","duration":1.25,"beginTime":0,"to":{"scalar":0.0040000000000000001}}],"removedOnCompletion":false}],"initialState":{"affineTransform":[1,0,0,1,0,0],"masksToBounds":false,"rotation":0,"scale":1,"position":{"pointX":507.48440933227539,"pointY":628.621826171875},"width":809.47780609130859,"sublayerTransform":[1,0,0,0,0,1,0,0,0,0,1,0,0,0,0,1],"contentsRect":{"y":0,"x":0,"width":1,"height":1},"opacity":1,"edgeAntialiasingMask":251658240,"height":567.39997863769531,"hidden":false,"anchorPoint":{"pointX":0.5,"pointY":0.5}},"layers":[{"animations":[{"additive":false,"timeOffset":0,"beginTime":0,"repeatCount":0,"fillMode":"both","duration":1.25,"autoreverses":false,"animations":[{"repeatCount":0,"removedOnCompletion":true,"from":{"scalar":1},"timingFunction":"EaseInEaseOut","additive":false,"timeOffset":0,"autoreverses":false,"property":"opacity","fillMode":"forwards","duration":0.41662499999999997,"beginTime":0,"to":{"scalar":0}},{"additive":false,"timeOffset":0,"beginTime":0.41662499999999997,"from":{"scalar":true},"repeatCount":0,"fillMode":"forwards","duration":0.83337499999999998,"autoreverses":false,"property":"hidden","to":{"scalar":true},"removedOnCompletion":true}],"removedOnCompletion":false}],"layers":[],"texturedRectangle":{"singleTextureOpacity":1,"textXHeight":0.62759999999999994,"textBaseline":0.96243617773056034,"isBackgroundTexture":true,"isVerticalText":false,"textColor":[0.99991613626480103,1,0.99988490343093872,1],"textureType":6},"initialState":{"affineTransform":[1,0,0,1,0,0],"masksToBounds":false,"rotation":0,"scale":1,"position":{"pointX":404.73892211914062,"pointY":283.69999939203262},"width":456,"sublayerTransform":[1,0,0,0,0,1,0,0,0,0,1,0,0,0,0,1],"contentsRect":{"y":0,"x":0,"width":1,"height":1},"opacity":1,"edgeAntialiasingMask":0,"height":50,"hidden":false,"anchorPoint":{"pointX":0.84536058860912655,"pointY":0.43243672490119933}},"texture":"AA7AF5330EFB1B04DADB648822DA59DD"}]},{"animations":[{"additive":false,"timeOffset":0,"beginTime":0,"repeatCount":0,"fillMode":"both","duration":1.25,"autoreverses":false,"animations":[{"repeatCount":0,"removedOnCompletion":true,"from":{"scalar":0.0050000000000000001},"timingFunction":"EaseInEaseOut","additive":false,"timeOffset":0,"autoreverses":false,"property":"zPosition","fillMode":"both","duration":1.25,"beginTime":0,"to":{"scalar":0.0050000000000000001}}],"removedOnCompletion":false}],"initialState":{"affineTransform":[1,0,0,1,0,0],"masksToBounds":false,"rotation":0,"scale":1,"position":{"pointX":507.48440933227539,"pointY":628.621826171875},"width":809.47780609130859,"sublayerTransform":[1,0,0,0,0,1,0,0,0,0,1,0,0,0,0,1],"contentsRect":{"y":0,"x":0,"width":1,"height":1},"opacity":1,"edgeAntialiasingMask":251658240,"height":567.39997863769531,"hidden":false,"anchorPoint":{"pointX":0.5,"pointY":0.5}},"layers":[{"animations":[{"additive":false,"timeOffset":0,"beginTime":0,"repeatCount":0,"fillMode":"both","duration":1.25,"autoreverses":false,"animations":[{"repeatCount":0,"removedOnCompletion":true,"from":{"scalar":1},"timingFunction":"EaseInEaseOut","additive":false,"timeOffset":0,"autoreverses":false,"property":"opacity","fillMode":"forwards","duration":0.41662499999999997,"beginTime":0,"to":{"scalar":0}},{"additive":false,"timeOffset":0,"beginTime":0.41662499999999997,"from":{"scalar":true},"repeatCount":0,"fillMode":"forwards","duration":0.83337499999999998,"autoreverses":false,"property":"hidden","to":{"scalar":true},"removedOnCompletion":true}],"removedOnCompletion":false}],"layers":[],"texturedRectangle":{"singleTextureOpacity":1,"textXHeight":0.52300000000000002,"textBaseline":0.78536348144213364,"isBackgroundTexture":true,"isVerticalText":false,"textColor":[0.99991613626480103,1,0.99988490343093872,1],"textureType":6},"initialState":{"affineTransform":[1,0,0,1,0,0],"masksToBounds":false,"rotation":0,"scale":1,"position":{"pointX":404.73892211914062,"pointY":283.69999939203262},"width":571,"sublayerTransform":[1,0,0,0,0,1,0,0,0,0,1,0,0,0,0,1],"contentsRect":{"y":0,"x":0,"width":1,"height":1},"opacity":1,"edgeAntialiasingMask":0,"height":60,"hidden":false,"anchorPoint":{"pointX":0.67510407776840931,"pointY":3.0103639374176661}},"texture":"0039962803FEF133B7DAD23E95B3B04F"}]},{"animations":[{"additive":false,"timeOffset":0,"beginTime":0,"repeatCount":0,"fillMode":"both","duration":1.25,"autoreverses":false,"animations":[{"repeatCount":0,"removedOnCompletion":true,"from":{"scalar":0.0060000000000000001},"timingFunction":"EaseInEaseOut","additive":false,"timeOffset":0,"autoreverses":false,"property":"zPosition","fillMode":"both","duration":1.25,"beginTime":0,"to":{"scalar":0.0060000000000000001}}],"removedOnCompletion":false}],"initialState":{"affineTransform":[1,0,0,1,0,0],"masksToBounds":false,"rotation":0,"scale":1,"position":{"pointX":507.48440933227539,"pointY":628.621826171875},"width":809.47780609130859,"sublayerTransform":[1,0,0,0,0,1,0,0,0,0,1,0,0,0,0,1],"contentsRect":{"y":0,"x":0,"width":1,"height":1},"opacity":1,"edgeAntialiasingMask":251658240,"height":567.39997863769531,"hidden":false,"anchorPoint":{"pointX":0.5,"pointY":0.5}},"layers":[{"animations":[{"additive":false,"timeOffset":0,"beginTime":0,"repeatCount":0,"fillMode":"both","duration":1.25,"autoreverses":false,"animations":[{"repeatCount":0,"removedOnCompletion":true,"from":{"scalar":1},"timingFunction":"EaseInEaseOut","additive":false,"timeOffset":0,"autoreverses":false,"property":"opacity","fillMode":"forwards","duration":0.41662499999999997,"beginTime":0,"to":{"scalar":0}},{"additive":false,"timeOffset":0,"beginTime":0.41662499999999997,"from":{"scalar":true},"repeatCount":0,"fillMode":"forwards","duration":0.83337499999999998,"autoreverses":false,"property":"hidden","to":{"scalar":true},"removedOnCompletion":true}],"removedOnCompletion":false}],"layers":[],"texturedRectangle":{"singleTextureOpacity":1,"textXHeight":0.64040816326530614,"textBaseline":0.96166956911281665,"isBackgroundTexture":true,"isVerticalText":false,"textColor":[0.99991613626480103,1,0.99988490343093872,1],"textureType":6},"initialState":{"affineTransform":[1,0,0,1,0,0],"masksToBounds":false,"rotation":0,"scale":1,"position":{"pointX":404.73892211914062,"pointY":283.69999939203262},"width":434,"sublayerTransform":[1,0,0,0,0,1,0,0,0,0,1,0,0,0,0,1],"contentsRect":{"y":0,"x":0,"width":1,"height":1},"opacity":1,"edgeAntialiasingMask":0,"height":49,"hidden":false,"anchorPoint":{"pointX":0.88821296867687027,"pointY":-4.4771053827538783}},"texture":"819791604C975CE9051B049C6D72FEE9"}]},{"animations":[{"additive":false,"timeOffset":0,"beginTime":0,"repeatCount":0,"fillMode":"both","duration":1.25,"autoreverses":false,"animations":[{"repeatCount":0,"removedOnCompletion":true,"from":{"scalar":0.0070000000000000001},"timingFunction":"EaseInEaseOut","additive":false,"timeOffset":0,"autoreverses":false,"property":"zPosition","fillMode":"both","duration":1.25,"beginTime":0,"to":{"scalar":0.0070000000000000001}}],"removedOnCompletion":false}],"initialState":{"affineTransform":[1,0,0,1,0,0],"masksToBounds":false,"rotation":0,"scale":1,"position":{"pointX":507.48440933227539,"pointY":628.621826171875},"width":809.47780609130859,"sublayerTransform":[1,0,0,0,0,1,0,0,0,0,1,0,0,0,0,1],"contentsRect":{"y":0,"x":0,"width":1,"height":1},"opacity":1,"edgeAntialiasingMask":251658240,"height":567.39997863769531,"hidden":false,"anchorPoint":{"pointX":0.5,"pointY":0.5}},"layers":[{"animations":[{"additive":false,"timeOffset":0,"beginTime":0,"repeatCount":0,"fillMode":"both","duration":1.25,"autoreverses":false,"animations":[{"repeatCount":0,"removedOnCompletion":true,"from":{"scalar":1},"timingFunction":"EaseInEaseOut","additive":false,"timeOffset":0,"autoreverses":false,"property":"opacity","fillMode":"forwards","duration":0.41662499999999997,"beginTime":0,"to":{"scalar":0}},{"additive":false,"timeOffset":0,"beginTime":0.41662499999999997,"from":{"scalar":true},"repeatCount":0,"fillMode":"forwards","duration":0.83337499999999998,"autoreverses":false,"property":"hidden","to":{"scalar":true},"removedOnCompletion":true}],"removedOnCompletion":false}],"layers":[],"texturedRectangle":{"singleTextureOpacity":1,"textXHeight":0.64040816326530614,"textBaseline":0.96166956911281665,"isBackgroundTexture":true,"isVerticalText":false,"textColor":[0.99991613626480103,1,0.99988490343093872,1],"textureType":6},"initialState":{"affineTransform":[1,0,0,1,0,0],"masksToBounds":false,"rotation":0,"scale":1,"position":{"pointX":404.73892211914062,"pointY":283.69999939203262},"width":369,"sublayerTransform":[1,0,0,0,0,1,0,0,0,0,1,0,0,0,0,1],"contentsRect":{"y":0,"x":0,"width":1,"height":1},"opacity":1,"edgeAntialiasingMask":0,"height":49,"hidden":false,"anchorPoint":{"pointX":1.0446732477120915,"pointY":-1.2117992603048986}},"texture":"689124FC3E296698DE64C81C316E84BD"}]},{"animations":[{"additive":false,"timeOffset":0,"beginTime":0,"repeatCount":0,"fillMode":"both","duration":1.25,"autoreverses":false,"animations":[{"repeatCount":0,"removedOnCompletion":true,"from":{"scalar":0.0080000000000000002},"timingFunction":"EaseInEaseOut","additive":false,"timeOffset":0,"autoreverses":false,"property":"zPosition","fillMode":"both","duration":1.25,"beginTime":0,"to":{"scalar":0.0080000000000000002}}],"removedOnCompletion":false}],"initialState":{"affineTransform":[1,0,0,1,0,0],"masksToBounds":false,"rotation":0,"scale":1,"position":{"pointX":507.48440933227539,"pointY":628.621826171875},"width":809.47780609130859,"sublayerTransform":[1,0,0,0,0,1,0,0,0,0,1,0,0,0,0,1],"contentsRect":{"y":0,"x":0,"width":1,"height":1},"opacity":1,"edgeAntialiasingMask":251658240,"height":567.39997863769531,"hidden":false,"anchorPoint":{"pointX":0.5,"pointY":0.5}},"layers":[{"animations":[{"additive":false,"timeOffset":0,"beginTime":0,"repeatCount":0,"fillMode":"both","duration":1.25,"autoreverses":false,"animations":[{"repeatCount":0,"removedOnCompletion":true,"from":{"scalar":1},"timingFunction":"EaseInEaseOut","additive":false,"timeOffset":0,"autoreverses":false,"property":"opacity","fillMode":"forwards","duration":0.41662499999999997,"beginTime":0,"to":{"scalar":0}},{"additive":false,"timeOffset":0,"beginTime":0.41662499999999997,"from":{"scalar":true},"repeatCount":0,"fillMode":"forwards","duration":0.83337499999999998,"autoreverses":false,"property":"hidden","to":{"scalar":true},"removedOnCompletion":true}],"removedOnCompletion":false}],"layers":[],"texturedRectangle":{"singleTextureOpacity":1,"textXHeight":0.64040816326530614,"textBaseline":0.96166956911281665,"isBackgroundTexture":true,"isVerticalText":false,"textColor":[0.99991613626480103,1,0.99988490343093872,1],"textureType":6},"initialState":{"affineTransform":[1,0,0,1,0,0],"masksToBounds":false,"rotation":0,"scale":1,"position":{"pointX":404.73892211914062,"pointY":283.69999939203262},"width":282,"sublayerTransform":[1,0,0,0,0,1,0,0,0,0,1,0,0,0,0,1],"contentsRect":{"y":0,"x":0,"width":1,"height":1},"opacity":1,"edgeAntialiasingMask":0,"height":49,"hidden":false,"anchorPoint":{"pointX":1.36696605817646,"pointY":-2.8444523215293884}},"texture":"2B389D0EE43EBB4A844CF8214803FA66"}]},{"animations":[{"additive":false,"timeOffset":0,"beginTime":0,"repeatCount":0,"fillMode":"both","duration":1.25,"autoreverses":false,"animations":[{"repeatCount":0,"removedOnCompletion":true,"from":{"scalar":0.0090000000000000011},"timingFunction":"EaseInEaseOut","additive":false,"timeOffset":0,"autoreverses":false,"property":"zPosition","fillMode":"both","duration":1.25,"beginTime":0,"to":{"scalar":0.0090000000000000011}}],"removedOnCompletion":false}],"initialState":{"affineTransform":[1,0,0,1,0,0],"masksToBounds":false,"rotation":0,"scale":1,"position":{"pointX":316.27392578125,"pointY":228.44105911254883},"width":442.548095703125,"sublayerTransform":[1,0,0,0,0,1,0,0,0,0,1,0,0,0,0,1],"contentsRect":{"y":0,"x":0,"width":1,"height":1},"opacity":1,"edgeAntialiasingMask":251658240,"height":86.879798889160156,"hidden":false,"anchorPoint":{"pointX":0.5,"pointY":0.5}},"layers":[{"animations":[{"additive":false,"timeOffset":0,"beginTime":0,"repeatCount":0,"fillMode":"both","duration":1.25,"autoreverses":false,"animations":[{"repeatCount":0,"removedOnCompletion":true,"from":{"scalar":1},"timingFunction":"EaseInEaseOut","additive":false,"timeOffset":0,"autoreverses":false,"property":"opacity","fillMode":"forwards","duration":0.41662499999999997,"beginTime":0,"to":{"scalar":0}},{"additive":false,"timeOffset":0,"beginTime":0.41662499999999997,"from":{"scalar":true},"repeatCount":0,"fillMode":"forwards","duration":0.83337499999999998,"autoreverses":false,"property":"hidden","to":{"scalar":true},"removedOnCompletion":true}],"removedOnCompletion":false}],"layers":[],"texturedRectangle":{"singleTextureOpacity":1,"textXHeight":0.62132399999999999,"textBaseline":0.92678263962268825,"isBackgroundTexture":true,"isVerticalText":false,"textColor":[1,1,1,1],"textureType":6},"initialState":{"affineTransform":[1,0,0,1,0,0],"masksToBounds":false,"rotation":0,"scale":1,"position":{"pointX":221.2740478515625,"pointY":43.439899444580078},"width":326,"sublayerTransform":[1,0,0,0,0,1,0,0,0,0,1,0,0,0,0,1],"contentsRect":{"y":0,"x":0,"width":1,"height":1},"opacity":1,"edgeAntialiasingMask":0,"height":50,"hidden":false,"anchorPoint":{"pointX":0.66955191957438653,"pointY":0.38882118225097656}},"texture":"903EA47FD208B72A1097F1E473D61AAA"}]},{"animations":[{"additive":false,"timeOffset":0,"beginTime":0,"repeatCount":0,"fillMode":"both","duration":1.25,"autoreverses":false,"animations":[{"repeatCount":0,"removedOnCompletion":true,"from":{"scalar":0.01},"timingFunction":"EaseInEaseOut","additive":false,"timeOffset":0,"autoreverses":false,"property":"zPosition","fillMode":"both","duration":1.25,"beginTime":0,"to":{"scalar":0.01}}],"removedOnCompletion":false}],"initialState":{"affineTransform":[1,0,0,1,0,0],"masksToBounds":false,"rotation":0,"scale":1,"position":{"pointX":507.48440933227539,"pointY":628.621826171875},"width":809.47780609130859,"sublayerTransform":[1,0,0,0,0,1,0,0,0,0,1,0,0,0,0,1],"contentsRect":{"y":0,"x":0,"width":1,"height":1},"opacity":1,"edgeAntialiasingMask":251658240,"height":567.39997863769531,"hidden":false,"anchorPoint":{"pointX":0.5,"pointY":0.5}},"layers":[{"animations":[{"additive":false,"timeOffset":0,"beginTime":0,"repeatCount":0,"fillMode":"both","duration":1.25,"autoreverses":false,"animations":[{"repeatCount":0,"removedOnCompletion":true,"from":{"scalar":0},"timingFunction":"EaseInEaseOut","additive":false,"timeOffset":0,"autoreverses":false,"property":"opacity","fillMode":"both","duration":0.41662499999999997,"beginTime":0.83337500000000009,"to":{"scalar":1}},{"additive":false,"timeOffset":0,"beginTime":0.83337500000000009,"from":{"scalar":false},"repeatCount":0,"fillMode":"forwards","duration":0.41662499999999991,"autoreverses":false,"property":"hidden","to":{"scalar":false},"removedOnCompletion":true}],"removedOnCompletion":false}],"layers":[],"texturedRectangle":{"singleTextureOpacity":1,"textXHeight":0.64040816326530614,"textBaseline":0.96166956911281665,"isBackgroundTexture":true,"isVerticalText":false,"textColor":[1,1,1,1],"textureType":6},"initialState":{"affineTransform":[1,0,0,1,0,0],"masksToBounds":false,"rotation":0,"scale":1,"position":{"pointX":404.73892211914062,"pointY":283.69999939203262},"width":495,"sublayerTransform":[1,0,0,0,0,1,0,0,0,0,1,0,0,0,0,1],"contentsRect":{"y":0,"x":0,"width":1,"height":1},"opacity":1,"edgeAntialiasingMask":0,"height":49,"hidden":true,"anchorPoint":{"pointX":0.77875642102174081,"pointY":2.0535068621440811}},"texture":"D9675965E73A9FBE25A5CF025DA70F5D"}]},{"animations":[{"additive":false,"timeOffset":0,"beginTime":0,"repeatCount":0,"fillMode":"both","duration":1.25,"autoreverses":false,"animations":[{"repeatCount":0,"removedOnCompletion":true,"from":{"scalar":0.010999999999999999},"timingFunction":"EaseInEaseOut","additive":false,"timeOffset":0,"autoreverses":false,"property":"zPosition","fillMode":"both","duration":1.25,"beginTime":0,"to":{"scalar":0.010999999999999999}}],"removedOnCompletion":false}],"initialState":{"affineTransform":[1,0,0,1,0,0],"masksToBounds":false,"rotation":0,"scale":1,"position":{"pointX":507.48440933227539,"pointY":628.621826171875},"width":809.47780609130859,"sublayerTransform":[1,0,0,0,0,1,0,0,0,0,1,0,0,0,0,1],"contentsRect":{"y":0,"x":0,"width":1,"height":1},"opacity":1,"edgeAntialiasingMask":251658240,"height":567.39997863769531,"hidden":false,"anchorPoint":{"pointX":0.5,"pointY":0.5}},"layers":[{"animations":[{"additive":false,"timeOffset":0,"beginTime":0,"repeatCount":0,"fillMode":"both","duration":1.25,"autoreverses":false,"animations":[{"repeatCount":0,"removedOnCompletion":true,"from":{"scalar":0},"timingFunction":"EaseInEaseOut","additive":false,"timeOffset":0,"autoreverses":false,"property":"opacity","fillMode":"both","duration":0.41662499999999997,"beginTime":0.83337500000000009,"to":{"scalar":1}},{"additive":false,"timeOffset":0,"beginTime":0.83337500000000009,"from":{"scalar":false},"repeatCount":0,"fillMode":"forwards","duration":0.41662499999999991,"autoreverses":false,"property":"hidden","to":{"scalar":false},"removedOnCompletion":true}],"removedOnCompletion":false}],"layers":[],"texturedRectangle":{"singleTextureOpacity":1,"textXHeight":0.62759999999999994,"textBaseline":0.96243617773056034,"isBackgroundTexture":true,"isVerticalText":false,"textColor":[1,1,1,1],"textureType":6},"initialState":{"affineTransform":[1,0,0,1,0,0],"masksToBounds":false,"rotation":0,"scale":1,"position":{"pointX":404.73892211914062,"pointY":283.69999939203262},"width":457,"sublayerTransform":[1,0,0,0,0,1,0,0,0,0,1,0,0,0,0,1],"contentsRect":{"y":0,"x":0,"width":1,"height":1},"opacity":1,"edgeAntialiasingMask":0,"height":50,"hidden":true,"anchorPoint":{"pointX":0.84351078425768433,"pointY":3.6324367249011993}},"texture":"70D46D016A3FCA36FDE43DAB46DE49AD"}]},{"animations":[{"additive":false,"timeOffset":0,"beginTime":0,"repeatCount":0,"fillMode":"both","duration":1.25,"autoreverses":false,"animations":[{"repeatCount":0,"removedOnCompletion":true,"from":{"scalar":0.012},"timingFunction":"EaseInEaseOut","additive":false,"timeOffset":0,"autoreverses":false,"property":"zPosition","fillMode":"both","duration":1.25,"beginTime":0,"to":{"scalar":0.012}}],"removedOnCompletion":false}],"initialState":{"affineTransform":[1,0,0,1,0,0],"masksToBounds":false,"rotation":0,"scale":1,"position":{"pointX":507.48440933227539,"pointY":628.621826171875},"width":809.47780609130859,"sublayerTransform":[1,0,0,0,0,1,0,0,0,0,1,0,0,0,0,1],"contentsRect":{"y":0,"x":0,"width":1,"height":1},"opacity":1,"edgeAntialiasingMask":251658240,"height":567.39997863769531,"hidden":false,"anchorPoint":{"pointX":0.5,"pointY":0.5}},"layers":[{"animations":[{"additive":false,"timeOffset":0,"beginTime":0,"repeatCount":0,"fillMode":"both","duration":1.25,"autoreverses":false,"animations":[{"repeatCount":0,"removedOnCompletion":true,"from":{"scalar":0},"timingFunction":"EaseInEaseOut","additive":false,"timeOffset":0,"autoreverses":false,"property":"opacity","fillMode":"both","duration":0.41662499999999997,"beginTime":0.83337500000000009,"to":{"scalar":1}},{"additive":false,"timeOffset":0,"beginTime":0.83337500000000009,"from":{"scalar":false},"repeatCount":0,"fillMode":"forwards","duration":0.41662499999999991,"autoreverses":false,"property":"hidden","to":{"scalar":false},"removedOnCompletion":true}],"removedOnCompletion":false}],"layers":[],"texturedRectangle":{"singleTextureOpacity":1,"textXHeight":0.62759999999999994,"textBaseline":0.96243617773056034,"isBackgroundTexture":true,"isVerticalText":false,"textColor":[1,1,1,1],"textureType":6},"initialState":{"affineTransform":[1,0,0,1,0,0],"masksToBounds":false,"rotation":0,"scale":1,"position":{"pointX":404.73892211914062,"pointY":283.69999939203262},"width":465,"sublayerTransform":[1,0,0,0,0,1,0,0,0,0,1,0,0,0,0,1],"contentsRect":{"y":0,"x":0,"width":1,"height":1},"opacity":1,"edgeAntialiasingMask":0,"height":50,"hidden":true,"anchorPoint":{"pointX":0.828998770765079,"pointY":-1.1675632750988008}},"texture":"836EA704896FC529AF870C42E7EF2500"}]},{"animations":[{"additive":false,"timeOffset":0,"beginTime":0,"repeatCount":0,"fillMode":"both","duration":1.25,"autoreverses":false,"animations":[{"repeatCount":0,"removedOnCompletion":true,"from":{"scalar":0.013000000000000001},"timingFunction":"EaseInEaseOut","additive":false,"timeOffset":0,"autoreverses":false,"property":"zPosition","fillMode":"both","duration":1.25,"beginTime":0,"to":{"scalar":0.013000000000000001}}],"removedOnCompletion":false}],"initialState":{"affineTransform":[1,0,0,1,0,0],"masksToBounds":false,"rotation":0,"scale":1,"position":{"pointX":507.48440933227539,"pointY":628.621826171875},"width":809.47780609130859,"sublayerTransform":[1,0,0,0,0,1,0,0,0,0,1,0,0,0,0,1],"contentsRect":{"y":0,"x":0,"width":1,"height":1},"opacity":1,"edgeAntialiasingMask":251658240,"height":567.39997863769531,"hidden":false,"anchorPoint":{"pointX":0.5,"pointY":0.5}},"layers":[{"animations":[{"additive":false,"timeOffset":0,"beginTime":0,"repeatCount":0,"fillMode":"both","duration":1.25,"autoreverses":false,"animations":[{"repeatCount":0,"removedOnCompletion":true,"from":{"scalar":0},"timingFunction":"EaseInEaseOut","additive":false,"timeOffset":0,"autoreverses":false,"property":"opacity","fillMode":"both","duration":0.41662499999999997,"beginTime":0.83337500000000009,"to":{"scalar":1}},{"additive":false,"timeOffset":0,"beginTime":0.83337500000000009,"from":{"scalar":false},"repeatCount":0,"fillMode":"forwards","duration":0.41662499999999991,"autoreverses":false,"property":"hidden","to":{"scalar":false},"removedOnCompletion":true}],"removedOnCompletion":false}],"layers":[],"texturedRectangle":{"singleTextureOpacity":1,"textXHeight":0.62759999999999994,"textBaseline":0.96243617773056034,"isBackgroundTexture":true,"isVerticalText":false,"textColor":[1,1,1,1],"textureType":6},"initialState":{"affineTransform":[1,0,0,1,0,0],"masksToBounds":false,"rotation":0,"scale":1,"position":{"pointX":404.73892211914062,"pointY":283.69999939203262},"width":274,"sublayerTransform":[1,0,0,0,0,1,0,0,0,0,1,0,0,0,0,1],"contentsRect":{"y":0,"x":0,"width":1,"height":1},"opacity":1,"edgeAntialiasingMask":0,"height":50,"hidden":true,"anchorPoint":{"pointX":1.406877475933437,"pointY":5.2324367249011994}},"texture":"12ECBE31370EBED8AC47C416E4745FC5"}]},{"animations":[{"additive":false,"timeOffset":0,"beginTime":0,"repeatCount":0,"fillMode":"both","duration":1.25,"autoreverses":false,"animations":[{"repeatCount":0,"removedOnCompletion":true,"from":{"scalar":0.014},"timingFunction":"EaseInEaseOut","additive":false,"timeOffset":0,"autoreverses":false,"property":"zPosition","fillMode":"both","duration":1.25,"beginTime":0,"to":{"scalar":0.014}}],"removedOnCompletion":false}],"initialState":{"affineTransform":[1,0,0,1,0,0],"masksToBounds":false,"rotation":0,"scale":1,"position":{"pointX":507.48440933227539,"pointY":628.621826171875},"width":809.47780609130859,"sublayerTransform":[1,0,0,0,0,1,0,0,0,0,1,0,0,0,0,1],"contentsRect":{"y":0,"x":0,"width":1,"height":1},"opacity":1,"edgeAntialiasingMask":251658240,"height":567.39997863769531,"hidden":false,"anchorPoint":{"pointX":0.5,"pointY":0.5}},"layers":[{"animations":[{"additive":false,"timeOffset":0,"beginTime":0,"repeatCount":0,"fillMode":"both","duration":1.25,"autoreverses":false,"animations":[{"repeatCount":0,"removedOnCompletion":true,"from":{"scalar":0},"timingFunction":"EaseInEaseOut","additive":false,"timeOffset":0,"autoreverses":false,"property":"opacity","fillMode":"both","duration":0.41662499999999997,"beginTime":0.83337500000000009,"to":{"scalar":1}},{"additive":false,"timeOffset":0,"beginTime":0.83337500000000009,"from":{"scalar":false},"repeatCount":0,"fillMode":"forwards","duration":0.41662499999999991,"autoreverses":false,"property":"hidden","to":{"scalar":false},"removedOnCompletion":true}],"removedOnCompletion":false}],"layers":[],"texturedRectangle":{"singleTextureOpacity":1,"textXHeight":0.55052631578947364,"textBaseline":0.7916106822197897,"isBackgroundTexture":true,"isVerticalText":false,"textColor":[1,1,1,1],"textureType":6},"initialState":{"affineTransform":[1,0,0,1,0,0],"masksToBounds":false,"rotation":0,"scale":1,"position":{"pointX":404.73892211914062,"pointY":283.69999939203262},"width":302,"sublayerTransform":[1,0,0,0,0,1,0,0,0,0,1,0,0,0,0,1],"contentsRect":{"y":0,"x":0,"width":1,"height":1},"opacity":1,"edgeAntialiasingMask":0,"height":57,"hidden":true,"anchorPoint":{"pointX":1.2764385046548401,"pointY":0.3266988814922801}},"texture":"598D726EDE84BC1689DB052B83637AB0"}]},{"animations":[{"additive":false,"timeOffset":0,"beginTime":0,"repeatCount":0,"fillMode":"both","duration":1.25,"autoreverses":false,"animations":[{"repeatCount":0,"removedOnCompletion":true,"from":{"scalar":0.014999999999999999},"timingFunction":"EaseInEaseOut","additive":false,"timeOffset":0,"autoreverses":false,"property":"zPosition","fillMode":"both","duration":1.25,"beginTime":0,"to":{"scalar":0.014999999999999999}}],"removedOnCompletion":false}],"initialState":{"affineTransform":[1,0,0,1,0,0],"masksToBounds":false,"rotation":0,"scale":1,"position":{"pointX":507.48440933227539,"pointY":628.621826171875},"width":809.47780609130859,"sublayerTransform":[1,0,0,0,0,1,0,0,0,0,1,0,0,0,0,1],"contentsRect":{"y":0,"x":0,"width":1,"height":1},"opacity":1,"edgeAntialiasingMask":251658240,"height":567.39997863769531,"hidden":false,"anchorPoint":{"pointX":0.5,"pointY":0.5}},"layers":[{"animations":[{"additive":false,"timeOffset":0,"beginTime":0,"repeatCount":0,"fillMode":"both","duration":1.25,"autoreverses":false,"animations":[{"repeatCount":0,"removedOnCompletion":true,"from":{"scalar":0},"timingFunction":"EaseInEaseOut","additive":false,"timeOffset":0,"autoreverses":false,"property":"opacity","fillMode":"both","duration":0.41662499999999997,"beginTime":0.83337500000000009,"to":{"scalar":1}},{"additive":false,"timeOffset":0,"beginTime":0.83337500000000009,"from":{"scalar":false},"repeatCount":0,"fillMode":"forwards","duration":0.41662499999999991,"autoreverses":false,"property":"hidden","to":{"scalar":false},"removedOnCompletion":true}],"removedOnCompletion":false}],"layers":[],"texturedRectangle":{"singleTextureOpacity":1,"textXHeight":0.62759999999999994,"textBaseline":0.96243617773056034,"isBackgroundTexture":true,"isVerticalText":false,"textColor":[1,1,1,1],"textureType":6},"initialState":{"affineTransform":[1,0,0,1,0,0],"masksToBounds":false,"rotation":0,"scale":1,"position":{"pointX":404.73892211914062,"pointY":283.69999939203262},"width":274,"sublayerTransform":[1,0,0,0,0,1,0,0,0,0,1,0,0,0,0,1],"contentsRect":{"y":0,"x":0,"width":1,"height":1},"opacity":1,"edgeAntialiasingMask":0,"height":50,"hidden":true,"anchorPoint":{"pointX":1.406877475933437,"pointY":-2.7675632750988006}},"texture":"EA78131353955516F02AF418FDBFC37F"}]},{"animations":[{"additive":false,"timeOffset":0,"beginTime":0,"repeatCount":0,"fillMode":"both","duration":1.25,"autoreverses":false,"animations":[{"repeatCount":0,"removedOnCompletion":true,"from":{"scalar":0.016},"timingFunction":"EaseInEaseOut","additive":false,"timeOffset":0,"autoreverses":false,"property":"zPosition","fillMode":"both","duration":1.25,"beginTime":0,"to":{"scalar":0.016}}],"removedOnCompletion":false}],"initialState":{"affineTransform":[1,0,0,1,0,0],"masksToBounds":false,"rotation":0,"scale":1,"position":{"pointX":507.48440933227539,"pointY":628.621826171875},"width":809.47780609130859,"sublayerTransform":[1,0,0,0,0,1,0,0,0,0,1,0,0,0,0,1],"contentsRect":{"y":0,"x":0,"width":1,"height":1},"opacity":1,"edgeAntialiasingMask":251658240,"height":567.39997863769531,"hidden":false,"anchorPoint":{"pointX":0.5,"pointY":0.5}},"layers":[{"animations":[{"additive":false,"timeOffset":0,"beginTime":0,"repeatCount":0,"fillMode":"both","duration":1.25,"autoreverses":false,"animations":[{"repeatCount":0,"removedOnCompletion":true,"from":{"scalar":0},"timingFunction":"EaseInEaseOut","additive":false,"timeOffset":0,"autoreverses":false,"property":"opacity","fillMode":"both","duration":0.41662499999999997,"beginTime":0.83337500000000009,"to":{"scalar":1}},{"additive":false,"timeOffset":0,"beginTime":0.83337500000000009,"from":{"scalar":false},"repeatCount":0,"fillMode":"forwards","duration":0.41662499999999991,"autoreverses":false,"property":"hidden","to":{"scalar":false},"removedOnCompletion":true}],"removedOnCompletion":false}],"layers":[],"texturedRectangle":{"singleTextureOpacity":1,"textXHeight":0.62759999999999994,"textBaseline":0.96243617773056034,"isBackgroundTexture":true,"isVerticalText":false,"textColor":[1,1,1,1],"textureType":6},"initialState":{"affineTransform":[1,0,0,1,0,0],"masksToBounds":false,"rotation":0,"scale":1,"position":{"pointX":404.73892211914062,"pointY":283.69999939203262},"width":431,"sublayerTransform":[1,0,0,0,0,1,0,0,0,0,1,0,0,0,0,1],"contentsRect":{"y":0,"x":0,"width":1,"height":1},"opacity":1,"edgeAntialiasingMask":0,"height":50,"hidden":true,"anchorPoint":{"pointX":0.89439542553541007,"pointY":-4.3675632750988003}},"texture":"678B3409415B9811738E10E21988BFEB"}]},{"animations":[{"additive":false,"timeOffset":0,"beginTime":0,"repeatCount":0,"fillMode":"both","duration":1.25,"autoreverses":false,"animations":[{"repeatCount":0,"removedOnCompletion":true,"from":{"scalar":0.017000000000000001},"timingFunction":"EaseInEaseOut","additive":false,"timeOffset":0,"autoreverses":false,"property":"zPosition","fillMode":"both","duration":1.25,"beginTime":0,"to":{"scalar":0.017000000000000001}}],"removedOnCompletion":false}],"initialState":{"affineTransform":[1,0,0,1,0,0],"masksToBounds":false,"rotation":0,"scale":1,"position":{"pointX":445.62939453125,"pointY":228.44105911254883},"width":701.259033203125,"sublayerTransform":[1,0,0,0,0,1,0,0,0,0,1,0,0,0,0,1],"contentsRect":{"y":0,"x":0,"width":1,"height":1},"opacity":1,"edgeAntialiasingMask":251658240,"height":86.879798889160156,"hidden":false,"anchorPoint":{"pointX":0.5,"pointY":0.5}},"layers":[{"animations":[{"additive":false,"timeOffset":0,"beginTime":0,"repeatCount":0,"fillMode":"both","duration":1.25,"autoreverses":false,"animations":[{"repeatCount":0,"removedOnCompletion":true,"from":{"scalar":0},"timingFunction":"EaseInEaseOut","additive":false,"timeOffset":0,"autoreverses":false,"property":"opacity","fillMode":"both","duration":0.41662499999999997,"beginTime":0.83337500000000009,"to":{"scalar":1}},{"additive":false,"timeOffset":0,"beginTime":0.83337500000000009,"from":{"scalar":false},"repeatCount":0,"fillMode":"forwards","duration":0.41662499999999991,"autoreverses":false,"property":"hidden","to":{"scalar":false},"removedOnCompletion":true}],"removedOnCompletion":false}],"layers":[],"texturedRectangle":{"singleTextureOpacity":1,"textXHeight":0.62132399999999999,"textBaseline":0.92678263962268825,"isBackgroundTexture":true,"isVerticalText":false,"textColor":[1,1,1,1],"textureType":6},"initialState":{"affineTransform":[1,0,0,1,0,0],"masksToBounds":false,"rotation":0,"scale":1,"position":{"pointX":350.6295166015625,"pointY":43.439899444580078},"width":619,"sublayerTransform":[1,0,0,0,0,1,0,0,0,0,1,0,0,0,0,1],"contentsRect":{"y":0,"x":0,"width":1,"height":1},"opacity":1,"edgeAntialiasingMask":0,"height":50,"hidden":true,"anchorPoint":{"pointX":0.56159837565630044,"pointY":0.38882118225097656}},"texture":"92685EF305F612428C44D7A698BF32EC"}]},{"animations":[{"additive":false,"timeOffset":0,"beginTime":0,"repeatCount":0,"fillMode":"both","duration":1.25,"autoreverses":false,"animations":[{"repeatCount":0,"removedOnCompletion":true,"from":{"scalar":0.018000000000000002},"timingFunction":"EaseInEaseOut","additive":false,"timeOffset":0,"autoreverses":false,"property":"zPosition","fillMode":"both","duration":1.25,"beginTime":0,"to":{"scalar":0.018000000000000002}}],"removedOnCompletion":false}],"initialState":{"affineTransform":[1,0,0,1,0,0],"masksToBounds":false,"rotation":0,"scale":1,"position":{"pointX":1394.142254576087,"pointY":579.25571140942316},"width":459.007653683424,"sublayerTransform":[1,0,0,0,0,1,0,0,0,0,1,0,0,0,0,1],"contentsRect":{"y":0,"x":0,"width":1,"height":1},"opacity":1,"edgeAntialiasingMask":251658240,"height":470.7337128579087,"hidden":false,"anchorPoint":{"pointX":0.5,"pointY":0.5}},"layers":[{"animations":[{"additive":false,"timeOffset":0,"beginTime":0,"repeatCount":0,"fillMode":"both","duration":1.25,"autoreverses":false,"animations":[{"repeatCount":0,"removedOnCompletion":true,"from":{"texture":"95BBD3B069FF32CAA2226F972BE9CC09"},"timingFunction":"EaseInEaseOut","additive":false,"timeOffset":0,"autoreverses":false,"property":"contents","fillMode":"both","duration":1.25,"beginTime":0,"to":{"texture":"95BBD3B069FF32CAA2226F972BE9CC09"}},{"repeatCount":0,"removedOnCompletion":true,"from":{"scalar":0},"timingFunction":"EaseInEaseOut","additive":false,"timeOffset":0,"autoreverses":false,"property":"transform.rotation.z","fillMode":"both","duration":1.25,"beginTime":0,"to":{"scalar":2.4454561930807497}}],"removedOnCompletion":false}],"layers":[],"texturedRectangle":{"singleTextureOpacity":1,"textXHeight":0,"shapePath":{"lineWidth":1,"flatness":0.59999999999999998,"lineCapStyle":0,"elements":[{"type":"MoveToPoint","points":[[225.37542146444321,1.88885498046875]]},{"type":"AddLine","points":[[225.37542146444321,53.064457908272743]]},{"type":"AddCurve","points":[[131.84916528506437,53.923918152016995],[53.198377573366088,116.96195098055614],[28.738510608673096,202.8408087939024]]},{"type":"AddLine","points":[[99.311643093824387,235.42543224990368]]},{"type":"AddCurve","points":[[110.48849557626454,175.63102644385799],[162.55486769888739,130.2387381321314],[225.37542146444321,129.32376849651337]]},{"type":"AddLine","points":[[225.37542146444321,176.02301844954491]]},{"type":"AddLine","points":[[343.57533650100231,88.955936715006828]]},{"type":"AddLine","points":[[225.37542146444321,1.88885498046875]]},{"type":"CloseSubpath"},{"type":"MoveToPoint","points":[[377.45044009387493,115.45110702514648]]},{"type":"AddLine","points":[[315.91066856682301,162.02937446534634]]},{"type":"AddCurve","points":[[358.27971336575865,199.74494426754973],[372.30919526879734,262.23808320040553],[346.64022682607174,315.63683825731277]]},{"type":"AddLine","points":[[304.86093239486217,294.78751854598522]]},{"type":"AddLine","points":[[329.98496755957603,439.40194888412952]]},{"type":"AddLine","points":[[460.646081417799,372.4986192882061]]},{"type":"AddLine","points":[[414.87436406314373,349.67325186729431]]},{"type":"AddCurve","points":[[453.95270026598882,269.48669610910292],[436.35817246725492,176.15788323313609],[377.45044009387493,115.45110702514648]]},{"type":"CloseSubpath"},{"type":"MoveToPoint","points":[[22.286109924316406,244.5394482165575]]},{"type":"AddLine","points":[[1.638427734375,389.92010113596916]]},{"type":"AddLine","points":[[46.684250012040138,365.64294356107712]]},{"type":"AddCurve","points":[[95.199852333011222,453.85888657957548],[199.00412826827232,492.77851199898578],[291.63351099193096,462.42895382642746]]},{"type":"AddLine","points":[[277.84150452911854,386.25029824674129]]},{"type":"AddCurve","points":[[217.31669436948141,411.65855567548715],[146.36032260112916,387.84059604968934],[113.86987213790417,329.50949972867966]]},{"type":"AddLine","points":[[154.96359899640083,307.410027384758]]},{"type":"AddLine","points":[[22.286109924316406,244.5394482165575]]},{"type":"CloseSubpath"},{"type":"MoveToPoint","points":[[22.286109924316406,244.5394482165575]]}],"windingRule":0,"lineJoinStyle":0,"miterLimit":10},"isBackgroundTexture":true,"textBaseline":0,"isVerticalText":false,"textureType":5},"initialState":{"affineTransform":[1,0,0,1,0,0],"masksToBounds":false,"rotation":0,"scale":1,"position":{"pointX":229.50382995605469,"pointY":235.36685180664062},"width":462,"sublayerTransform":[1,0,0,0,0,1,0,0,0,0,1,0,0,0,0,1],"contentsRect":{"y":0,"x":0,"width":1,"height":1},"opacity":1,"edgeAntialiasingMask":0,"height":474,"hidden":false,"anchorPoint":{"pointX":0.50030791707885214,"pointY":0.50053946579558939}},"texture":"95BBD3B069FF32CAA2226F972BE9CC09"}]}]},"effects":[],"duration":1.25,"type":"transition","attributes":{"direction":0},"name":"apple:magic-move-implied-motion-path","objectID":"0"}],"automaticPlay":false,"hyperlinks":[],"accessibility":[{"text":"Ciclo di vita","targetRectangle":{"y":190.00115966796875,"x":98.9998779296875,"width":325.57140034520006,"height":78.405998796224594}},{"text":"Studio di fattibilità","targetRectangle":{"y":348.92183685302734,"x":143.87099497299641,"width":534.36000000000013,"height":79.399998784065247}},{"text":"Progetto esecutivo","targetRectangle":{"y":428.92183685302734,"x":143.87099497299641,"width":549.18000000000006,"height":79.399998784065247}},{"text":"Realizzazione","targetRectangle":{"y":508.92183685302734,"x":143.87099497299641,"width":392.33999999999992,"height":79.399998784065247}},{"text":"Test o collaudo","targetRectangle":{"y":588.92183685302734,"x":143.87099497299641,"width":434.16000000000008,"height":79.399998784065247}},{"text":"Avviamento","targetRectangle":{"y":668.92183685302734,"x":143.87099497299641,"width":347.15999999999997,"height":79.399998784065247}},{"text":"Esercizio","targetRectangle":{"y":748.92183685302734,"x":143.87099497299641,"width":260.57999999999998,"height":79.399998784065247}},{"text":"Manutenzione","targetRectangle":{"y":828.92183685302734,"x":143.87099497299641,"width":412.5,"height":79.399998784065247}},{"text":"Sistema informatico\\t","targetRectangle":{"y":67.050674438476562,"x":98.9998779296875,"width":959.97596740722656,"height":122.06999811530113}}],"baseLayer":{"animations":[],"initialState":{"affineTransform":[1,0,0,1,0,0],"masksToBounds":false,"rotation":0,"scale":1,"position":{"pointX":960,"pointY":540},"width":1920,"sublayerTransform":[1,0,0,0,0,1,0,0,0,0,1,0,0,0,0,1],"contentsRect":{"y":0,"x":0,"width":1,"height":1},"opacity":1,"edgeAntialiasingMask":251658240,"height":1080,"hidden":false,"anchorPoint":{"pointX":0.5,"pointY":0.5}},"objectID":"0","layers":[{"animations":[],"initialState":{"affineTransform":[1,0,0,1,0,0],"masksToBounds":false,"rotation":0,"scale":1,"position":{"pointX":960,"pointY":540},"width":1920,"sublayerTransform":[1,0,0,0,0,1,0,0,0,0,1,-0.00035007912466775983,0,0,0,1],"contentsRect":{"y":0,"x":0,"width":1,"height":1},"opacity":1,"edgeAntialiasingMask":251658240,"height":1080,"hidden":false,"anchorPoint":{"pointX":0.5,"pointY":0.5}},"layers":[{"animations":[],"initialState":{"affineTransform":[1,0,0,1,0,0],"masksToBounds":false,"rotation":0,"scale":1,"position":{"pointX":960,"pointY":540},"width":1920,"sublayerTransform":[1,0,0,0,0,1,0,0,0,0,1,0,0,0,0,1],"contentsRect":{"y":0,"x":0,"width":1,"height":1},"opacity":1,"edgeAntialiasingMask":251658240,"height":1080,"hidden":false,"anchorPoint":{"pointX":0.5,"pointY":0.5}},"layers":[{"animations":[],"layers":[],"texturedRectangle":{"isBackgroundTexture":true,"singleTextureOpacity":1,"textureType":1,"textBaseline":0,"textXHeight":0,"isVerticalText":false},"initialState":{"affineTransform":[1,0,0,1,0,0],"masksToBounds":false,"rotation":0,"scale":1,"position":{"pointX":960,"pointY":540},"width":1920,"sublayerTransform":[1,0,0,0,0,1,0,0,0,0,1,0,0,0,0,1],"contentsRect":{"y":0,"x":0,"width":1,"height":1},"opacity":1,"edgeAntialiasingMask":0,"height":1080,"hidden":false,"anchorPoint":{"pointX":0.5,"pointY":0.5}},"texture":"3FC21BC9DAF17E097D2300B1C642C405"}]}]},{"animations":[],"initialState":{"affineTransform":[1,0,0,1,0,0],"masksToBounds":false,"rotation":0,"scale":1,"position":{"pointX":576.22085571289062,"pointY":127.45227813720703},"width":962.44195556640625,"sublayerTransform":[1,0,0,0,0,1,0,0,0,0,1,0,0,0,0,1],"contentsRect":{"y":0,"x":0,"width":1,"height":1},"opacity":1,"edgeAntialiasingMask":251658240,"height":130.80320739746094,"hidden":false,"anchorPoint":{"pointX":0.5,"pointY":0.5}},"layers":[{"animations":[],"layers":[],"texturedRectangle":{"singleTextureOpacity":1,"textXHeight":0.63998684210526324,"textBaseline":0.95606093540003423,"isBackgroundTexture":true,"isVerticalText":false,"textColor":[1,1,1,1],"textureType":6},"initialState":{"affineTransform":[1,0,0,1,0,0],"masksToBounds":false,"rotation":0,"scale":1,"position":{"pointX":481.22097778320312,"pointY":65.401603698730469},"width":885,"sublayerTransform":[1,0,0,0,0,1,0,0,0,0,1,0,0,0,0,1],"contentsRect":{"y":0,"x":0,"width":1,"height":1},"opacity":1,"edgeAntialiasingMask":0,"height":76,"hidden":false,"anchorPoint":{"pointX":0.53923260532530015,"pointY":0.41384576496325043}},"texture":"20971E7F33692F6B8FCD8DBF7F8B5D0E"}]},{"animations":[],"initialState":{"affineTransform":[1,0,0,1,0,0],"masksToBounds":false,"rotation":0,"scale":1,"position":{"pointX":507.48440933227539,"pointY":628.621826171875},"width":809.47780609130859,"sublayerTransform":[1,0,0,0,0,1,0,0,0,0,1,0,0,0,0,1],"contentsRect":{"y":0,"x":0,"width":1,"height":1},"opacity":1,"edgeAntialiasingMask":251658240,"height":567.39997863769531,"hidden":false,"anchorPoint":{"pointX":0.5,"pointY":0.5}},"layers":[{"animations":[],"layers":[],"texturedRectangle":{"singleTextureOpacity":1,"textXHeight":0.62759999999999994,"textBaseline":0.96243617773056034,"isBackgroundTexture":true,"isVerticalText":false,"textColor":[0.99991613626480103,1,0.99988490343093872,1],"textureType":6},"initialState":{"affineTransform":[1,0,0,1,0,0],"masksToBounds":false,"rotation":0,"scale":1,"position":{"pointX":404.73892211914062,"pointY":283.69999939203262},"width":554,"sublayerTransform":[1,0,0,0,0,1,0,0,0,0,1,0,0,0,0,1],"contentsRect":{"y":0,"x":0,"width":1,"height":1},"opacity":1,"edgeAntialiasingMask":0,"height":50,"hidden":false,"anchorPoint":{"pointX":0.69582026788043627,"pointY":5.2324367249011994}},"texture":"02DA42B8BBA00178F5E0C7A57CF788DE"}]},{"animations":[],"initialState":{"affineTransform":[1,0,0,1,0,0],"masksToBounds":false,"rotation":0,"scale":1,"position":{"pointX":507.48440933227539,"pointY":628.621826171875},"width":809.47780609130859,"sublayerTransform":[1,0,0,0,0,1,0,0,0,0,1,0,0,0,0,1],"contentsRect":{"y":0,"x":0,"width":1,"height":1},"opacity":1,"edgeAntialiasingMask":251658240,"height":567.39997863769531,"hidden":false,"anchorPoint":{"pointX":0.5,"pointY":0.5}},"layers":[{"animations":[],"layers":[],"texturedRectangle":{"singleTextureOpacity":1,"textXHeight":0.62759999999999994,"textBaseline":0.96243617773056034,"isBackgroundTexture":true,"isVerticalText":false,"textColor":[0.99991613626480103,1,0.99988490343093872,1],"textureType":6},"initialState":{"affineTransform":[1,0,0,1,0,0],"masksToBounds":false,"rotation":0,"scale":1,"position":{"pointX":404.73892211914062,"pointY":283.69999939203262},"width":414,"sublayerTransform":[1,0,0,0,0,1,0,0,0,0,1,0,0,0,0,1],"contentsRect":{"y":0,"x":0,"width":1,"height":1},"opacity":1,"edgeAntialiasingMask":0,"height":50,"hidden":false,"anchorPoint":{"pointX":0.93112180774338582,"pointY":2.0324367249011992}},"texture":"3AB81D1FC31F83B945888240D4239869"}]},{"animations":[],"initialState":{"affineTransform":[1,0,0,1,0,0],"masksToBounds":false,"rotation":0,"scale":1,"position":{"pointX":507.48440933227539,"pointY":628.621826171875},"width":809.47780609130859,"sublayerTransform":[1,0,0,0,0,1,0,0,0,0,1,0,0,0,0,1],"contentsRect":{"y":0,"x":0,"width":1,"height":1},"opacity":1,"edgeAntialiasingMask":251658240,"height":567.39997863769531,"hidden":false,"anchorPoint":{"pointX":0.5,"pointY":0.5}},"layers":[{"animations":[],"layers":[],"texturedRectangle":{"singleTextureOpacity":1,"textXHeight":0.62759999999999994,"textBaseline":0.96243617773056034,"isBackgroundTexture":true,"isVerticalText":false,"textColor":[0.99991613626480103,1,0.99988490343093872,1],"textureType":6},"initialState":{"affineTransform":[1,0,0,1,0,0],"masksToBounds":false,"rotation":0,"scale":1,"position":{"pointX":404.73892211914062,"pointY":283.69999939203262},"width":456,"sublayerTransform":[1,0,0,0,0,1,0,0,0,0,1,0,0,0,0,1],"contentsRect":{"y":0,"x":0,"width":1,"height":1},"opacity":1,"edgeAntialiasingMask":0,"height":50,"hidden":false,"anchorPoint":{"pointX":0.84536058860912655,"pointY":0.43243672490119933}},"texture":"AA7AF5330EFB1B04DADB648822DA59DD"}]},{"animations":[],"initialState":{"affineTransform":[1,0,0,1,0,0],"masksToBounds":false,"rotation":0,"scale":1,"position":{"pointX":507.48440933227539,"pointY":628.621826171875},"width":809.47780609130859,"sublayerTransform":[1,0,0,0,0,1,0,0,0,0,1,0,0,0,0,1],"contentsRect":{"y":0,"x":0,"width":1,"height":1},"opacity":1,"edgeAntialiasingMask":251658240,"height":567.39997863769531,"hidden":false,"anchorPoint":{"pointX":0.5,"pointY":0.5}},"layers":[{"animations":[],"layers":[],"texturedRectangle":{"singleTextureOpacity":1,"textXHeight":0.52300000000000002,"textBaseline":0.78536348144213364,"isBackgroundTexture":true,"isVerticalText":false,"textColor":[0.99991613626480103,1,0.99988490343093872,1],"textureType":6},"initialState":{"affineTransform":[1,0,0,1,0,0],"masksToBounds":false,"rotation":0,"scale":1,"position":{"pointX":404.73892211914062,"pointY":283.69999939203262},"width":571,"sublayerTransform":[1,0,0,0,0,1,0,0,0,0,1,0,0,0,0,1],"contentsRect":{"y":0,"x":0,"width":1,"height":1},"opacity":1,"edgeAntialiasingMask":0,"height":60,"hidden":false,"anchorPoint":{"pointX":0.67510407776840931,"pointY":3.0103639374176661}},"texture":"0039962803FEF133B7DAD23E95B3B04F"}]},{"animations":[],"initialState":{"affineTransform":[1,0,0,1,0,0],"masksToBounds":false,"rotation":0,"scale":1,"position":{"pointX":507.48440933227539,"pointY":628.621826171875},"width":809.47780609130859,"sublayerTransform":[1,0,0,0,0,1,0,0,0,0,1,0,0,0,0,1],"contentsRect":{"y":0,"x":0,"width":1,"height":1},"opacity":1,"edgeAntialiasingMask":251658240,"height":567.39997863769531,"hidden":false,"anchorPoint":{"pointX":0.5,"pointY":0.5}},"layers":[{"animations":[],"layers":[],"texturedRectangle":{"singleTextureOpacity":1,"textXHeight":0.64040816326530614,"textBaseline":0.96166956911281665,"isBackgroundTexture":true,"isVerticalText":false,"textColor":[0.99991613626480103,1,0.99988490343093872,1],"textureType":6},"initialState":{"affineTransform":[1,0,0,1,0,0],"masksToBounds":false,"rotation":0,"scale":1,"position":{"pointX":404.73892211914062,"pointY":283.69999939203262},"width":434,"sublayerTransform":[1,0,0,0,0,1,0,0,0,0,1,0,0,0,0,1],"contentsRect":{"y":0,"x":0,"width":1,"height":1},"opacity":1,"edgeAntialiasingMask":0,"height":49,"hidden":false,"anchorPoint":{"pointX":0.88821296867687027,"pointY":-4.4771053827538783}},"texture":"819791604C975CE9051B049C6D72FEE9"}]},{"animations":[],"initialState":{"affineTransform":[1,0,0,1,0,0],"masksToBounds":false,"rotation":0,"scale":1,"position":{"pointX":507.48440933227539,"pointY":628.621826171875},"width":809.47780609130859,"sublayerTransform":[1,0,0,0,0,1,0,0,0,0,1,0,0,0,0,1],"contentsRect":{"y":0,"x":0,"width":1,"height":1},"opacity":1,"edgeAntialiasingMask":251658240,"height":567.39997863769531,"hidden":false,"anchorPoint":{"pointX":0.5,"pointY":0.5}},"layers":[{"animations":[],"layers":[],"texturedRectangle":{"singleTextureOpacity":1,"textXHeight":0.64040816326530614,"textBaseline":0.96166956911281665,"isBackgroundTexture":true,"isVerticalText":false,"textColor":[0.99991613626480103,1,0.99988490343093872,1],"textureType":6},"initialState":{"affineTransform":[1,0,0,1,0,0],"masksToBounds":false,"rotation":0,"scale":1,"position":{"pointX":404.73892211914062,"pointY":283.69999939203262},"width":369,"sublayerTransform":[1,0,0,0,0,1,0,0,0,0,1,0,0,0,0,1],"contentsRect":{"y":0,"x":0,"width":1,"height":1},"opacity":1,"edgeAntialiasingMask":0,"height":49,"hidden":false,"anchorPoint":{"pointX":1.0446732477120915,"pointY":-1.2117992603048986}},"texture":"689124FC3E296698DE64C81C316E84BD"}]},{"animations":[],"initialState":{"affineTransform":[1,0,0,1,0,0],"masksToBounds":false,"rotation":0,"scale":1,"position":{"pointX":507.48440933227539,"pointY":628.621826171875},"width":809.47780609130859,"sublayerTransform":[1,0,0,0,0,1,0,0,0,0,1,0,0,0,0,1],"contentsRect":{"y":0,"x":0,"width":1,"height":1},"opacity":1,"edgeAntialiasingMask":251658240,"height":567.39997863769531,"hidden":false,"anchorPoint":{"pointX":0.5,"pointY":0.5}},"layers":[{"animations":[],"layers":[],"texturedRectangle":{"singleTextureOpacity":1,"textXHeight":0.64040816326530614,"textBaseline":0.96166956911281665,"isBackgroundTexture":true,"isVerticalText":false,"textColor":[0.99991613626480103,1,0.99988490343093872,1],"textureType":6},"initialState":{"affineTransform":[1,0,0,1,0,0],"masksToBounds":false,"rotation":0,"scale":1,"position":{"pointX":404.73892211914062,"pointY":283.69999939203262},"width":282,"sublayerTransform":[1,0,0,0,0,1,0,0,0,0,1,0,0,0,0,1],"contentsRect":{"y":0,"x":0,"width":1,"height":1},"opacity":1,"edgeAntialiasingMask":0,"height":49,"hidden":false,"anchorPoint":{"pointX":1.36696605817646,"pointY":-2.8444523215293884}},"texture":"2B389D0EE43EBB4A844CF8214803FA66"}]},{"animations":[],"initialState":{"affineTransform":[1,0,0,1,0,0],"masksToBounds":false,"rotation":0,"scale":1,"position":{"pointX":316.27392578125,"pointY":228.44105911254883},"width":442.548095703125,"sublayerTransform":[1,0,0,0,0,1,0,0,0,0,1,0,0,0,0,1],"contentsRect":{"y":0,"x":0,"width":1,"height":1},"opacity":1,"edgeAntialiasingMask":251658240,"height":86.879798889160156,"hidden":false,"anchorPoint":{"pointX":0.5,"pointY":0.5}},"layers":[{"animations":[],"layers":[],"texturedRectangle":{"singleTextureOpacity":1,"textXHeight":0.62132399999999999,"textBaseline":0.92678263962268825,"isBackgroundTexture":true,"isVerticalText":false,"textColor":[1,1,1,1],"textureType":6},"initialState":{"affineTransform":[1,0,0,1,0,0],"masksToBounds":false,"rotation":0,"scale":1,"position":{"pointX":221.2740478515625,"pointY":43.439899444580078},"width":326,"sublayerTransform":[1,0,0,0,0,1,0,0,0,0,1,0,0,0,0,1],"contentsRect":{"y":0,"x":0,"width":1,"height":1},"opacity":1,"edgeAntialiasingMask":0,"height":50,"hidden":false,"anchorPoint":{"pointX":0.66955191957438653,"pointY":0.38882118225097656}},"texture":"903EA47FD208B72A1097F1E473D61AAA"}]},{"animations":[],"initialState":{"affineTransform":[1,0,0,1,0,0],"masksToBounds":false,"rotation":0,"scale":1,"position":{"pointX":507.48440933227539,"pointY":628.621826171875},"width":809.47780609130859,"sublayerTransform":[1,0,0,0,0,1,0,0,0,0,1,0,0,0,0,1],"contentsRect":{"y":0,"x":0,"width":1,"height":1},"opacity":1,"edgeAntialiasingMask":251658240,"height":567.39997863769531,"hidden":false,"anchorPoint":{"pointX":0.5,"pointY":0.5}},"layers":[{"animations":[],"layers":[],"texturedRectangle":{"singleTextureOpacity":1,"textXHeight":0.64040816326530614,"textBaseline":0.96166956911281665,"isBackgroundTexture":true,"isVerticalText":false,"textColor":[1,1,1,1],"textureType":6},"initialState":{"affineTransform":[1,0,0,1,0,0],"masksToBounds":false,"rotation":0,"scale":1,"position":{"pointX":404.73892211914062,"pointY":283.69999939203262},"width":495,"sublayerTransform":[1,0,0,0,0,1,0,0,0,0,1,0,0,0,0,1],"contentsRect":{"y":0,"x":0,"width":1,"height":1},"opacity":1,"edgeAntialiasingMask":0,"height":49,"hidden":true,"anchorPoint":{"pointX":0.77875642102174081,"pointY":2.0535068621440811}},"texture":"D9675965E73A9FBE25A5CF025DA70F5D"}]},{"animations":[],"initialState":{"affineTransform":[1,0,0,1,0,0],"masksToBounds":false,"rotation":0,"scale":1,"position":{"pointX":507.48440933227539,"pointY":628.621826171875},"width":809.47780609130859,"sublayerTransform":[1,0,0,0,0,1,0,0,0,0,1,0,0,0,0,1],"contentsRect":{"y":0,"x":0,"width":1,"height":1},"opacity":1,"edgeAntialiasingMask":251658240,"height":567.39997863769531,"hidden":false,"anchorPoint":{"pointX":0.5,"pointY":0.5}},"layers":[{"animations":[],"layers":[],"texturedRectangle":{"singleTextureOpacity":1,"textXHeight":0.62759999999999994,"textBaseline":0.96243617773056034,"isBackgroundTexture":true,"isVerticalText":false,"textColor":[1,1,1,1],"textureType":6},"initialState":{"affineTransform":[1,0,0,1,0,0],"masksToBounds":false,"rotation":0,"scale":1,"position":{"pointX":404.73892211914062,"pointY":283.69999939203262},"width":457,"sublayerTransform":[1,0,0,0,0,1,0,0,0,0,1,0,0,0,0,1],"contentsRect":{"y":0,"x":0,"width":1,"height":1},"opacity":1,"edgeAntialiasingMask":0,"height":50,"hidden":true,"anchorPoint":{"pointX":0.84351078425768433,"pointY":3.6324367249011993}},"texture":"70D46D016A3FCA36FDE43DAB46DE49AD"}]},{"animations":[],"initialState":{"affineTransform":[1,0,0,1,0,0],"masksToBounds":false,"rotation":0,"scale":1,"position":{"pointX":507.48440933227539,"pointY":628.621826171875},"width":809.47780609130859,"sublayerTransform":[1,0,0,0,0,1,0,0,0,0,1,0,0,0,0,1],"contentsRect":{"y":0,"x":0,"width":1,"height":1},"opacity":1,"edgeAntialiasingMask":251658240,"height":567.39997863769531,"hidden":false,"anchorPoint":{"pointX":0.5,"pointY":0.5}},"layers":[{"animations":[],"layers":[],"texturedRectangle":{"singleTextureOpacity":1,"textXHeight":0.62759999999999994,"textBaseline":0.96243617773056034,"isBackgroundTexture":true,"isVerticalText":false,"textColor":[1,1,1,1],"textureType":6},"initialState":{"affineTransform":[1,0,0,1,0,0],"masksToBounds":false,"rotation":0,"scale":1,"position":{"pointX":404.73892211914062,"pointY":283.69999939203262},"width":465,"sublayerTransform":[1,0,0,0,0,1,0,0,0,0,1,0,0,0,0,1],"contentsRect":{"y":0,"x":0,"width":1,"height":1},"opacity":1,"edgeAntialiasingMask":0,"height":50,"hidden":true,"anchorPoint":{"pointX":0.828998770765079,"pointY":-1.1675632750988008}},"texture":"836EA704896FC529AF870C42E7EF2500"}]},{"animations":[],"initialState":{"affineTransform":[1,0,0,1,0,0],"masksToBounds":false,"rotation":0,"scale":1,"position":{"pointX":507.48440933227539,"pointY":628.621826171875},"width":809.47780609130859,"sublayerTransform":[1,0,0,0,0,1,0,0,0,0,1,0,0,0,0,1],"contentsRect":{"y":0,"x":0,"width":1,"height":1},"opacity":1,"edgeAntialiasingMask":251658240,"height":567.39997863769531,"hidden":false,"anchorPoint":{"pointX":0.5,"pointY":0.5}},"layers":[{"animations":[],"layers":[],"texturedRectangle":{"singleTextureOpacity":1,"textXHeight":0.62759999999999994,"textBaseline":0.96243617773056034,"isBackgroundTexture":true,"isVerticalText":false,"textColor":[1,1,1,1],"textureType":6},"initialState":{"affineTransform":[1,0,0,1,0,0],"masksToBounds":false,"rotation":0,"scale":1,"position":{"pointX":404.73892211914062,"pointY":283.69999939203262},"width":274,"sublayerTransform":[1,0,0,0,0,1,0,0,0,0,1,0,0,0,0,1],"contentsRect":{"y":0,"x":0,"width":1,"height":1},"opacity":1,"edgeAntialiasingMask":0,"height":50,"hidden":true,"anchorPoint":{"pointX":1.406877475933437,"pointY":5.2324367249011994}},"texture":"12ECBE31370EBED8AC47C416E4745FC5"}]},{"animations":[],"initialState":{"affineTransform":[1,0,0,1,0,0],"masksToBounds":false,"rotation":0,"scale":1,"position":{"pointX":507.48440933227539,"pointY":628.621826171875},"width":809.47780609130859,"sublayerTransform":[1,0,0,0,0,1,0,0,0,0,1,0,0,0,0,1],"contentsRect":{"y":0,"x":0,"width":1,"height":1},"opacity":1,"edgeAntialiasingMask":251658240,"height":567.39997863769531,"hidden":false,"anchorPoint":{"pointX":0.5,"pointY":0.5}},"layers":[{"animations":[],"layers":[],"texturedRectangle":{"singleTextureOpacity":1,"textXHeight":0.55052631578947364,"textBaseline":0.7916106822197897,"isBackgroundTexture":true,"isVerticalText":false,"textColor":[1,1,1,1],"textureType":6},"initialState":{"affineTransform":[1,0,0,1,0,0],"masksToBounds":false,"rotation":0,"scale":1,"position":{"pointX":404.73892211914062,"pointY":283.69999939203262},"width":302,"sublayerTransform":[1,0,0,0,0,1,0,0,0,0,1,0,0,0,0,1],"contentsRect":{"y":0,"x":0,"width":1,"height":1},"opacity":1,"edgeAntialiasingMask":0,"height":57,"hidden":true,"anchorPoint":{"pointX":1.2764385046548401,"pointY":0.3266988814922801}},"texture":"598D726EDE84BC1689DB052B83637AB0"}]},{"animations":[],"initialState":{"affineTransform":[1,0,0,1,0,0],"masksToBounds":false,"rotation":0,"scale":1,"position":{"pointX":507.48440933227539,"pointY":628.621826171875},"width":809.47780609130859,"sublayerTransform":[1,0,0,0,0,1,0,0,0,0,1,0,0,0,0,1],"contentsRect":{"y":0,"x":0,"width":1,"height":1},"opacity":1,"edgeAntialiasingMask":251658240,"height":567.39997863769531,"hidden":false,"anchorPoint":{"pointX":0.5,"pointY":0.5}},"layers":[{"animations":[],"layers":[],"texturedRectangle":{"singleTextureOpacity":1,"textXHeight":0.62759999999999994,"textBaseline":0.96243617773056034,"isBackgroundTexture":true,"isVerticalText":false,"textColor":[1,1,1,1],"textureType":6},"initialState":{"affineTransform":[1,0,0,1,0,0],"masksToBounds":false,"rotation":0,"scale":1,"position":{"pointX":404.73892211914062,"pointY":283.69999939203262},"width":274,"sublayerTransform":[1,0,0,0,0,1,0,0,0,0,1,0,0,0,0,1],"contentsRect":{"y":0,"x":0,"width":1,"height":1},"opacity":1,"edgeAntialiasingMask":0,"height":50,"hidden":true,"anchorPoint":{"pointX":1.406877475933437,"pointY":-2.7675632750988006}},"texture":"EA78131353955516F02AF418FDBFC37F"}]},{"animations":[],"initialState":{"affineTransform":[1,0,0,1,0,0],"masksToBounds":false,"rotation":0,"scale":1,"position":{"pointX":507.48440933227539,"pointY":628.621826171875},"width":809.47780609130859,"sublayerTransform":[1,0,0,0,0,1,0,0,0,0,1,0,0,0,0,1],"contentsRect":{"y":0,"x":0,"width":1,"height":1},"opacity":1,"edgeAntialiasingMask":251658240,"height":567.39997863769531,"hidden":false,"anchorPoint":{"pointX":0.5,"pointY":0.5}},"layers":[{"animations":[],"layers":[],"texturedRectangle":{"singleTextureOpacity":1,"textXHeight":0.62759999999999994,"textBaseline":0.96243617773056034,"isBackgroundTexture":true,"isVerticalText":false,"textColor":[1,1,1,1],"textureType":6},"initialState":{"affineTransform":[1,0,0,1,0,0],"masksToBounds":false,"rotation":0,"scale":1,"position":{"pointX":404.73892211914062,"pointY":283.69999939203262},"width":431,"sublayerTransform":[1,0,0,0,0,1,0,0,0,0,1,0,0,0,0,1],"contentsRect":{"y":0,"x":0,"width":1,"height":1},"opacity":1,"edgeAntialiasingMask":0,"height":50,"hidden":true,"anchorPoint":{"pointX":0.89439542553541007,"pointY":-4.3675632750988003}},"texture":"678B3409415B9811738E10E21988BFEB"}]},{"animations":[],"initialState":{"affineTransform":[1,0,0,1,0,0],"masksToBounds":false,"rotation":0,"scale":1,"position":{"pointX":445.62939453125,"pointY":228.44105911254883},"width":701.259033203125,"sublayerTransform":[1,0,0,0,0,1,0,0,0,0,1,0,0,0,0,1],"contentsRect":{"y":0,"x":0,"width":1,"height":1},"opacity":1,"edgeAntialiasingMask":251658240,"height":86.879798889160156,"hidden":false,"anchorPoint":{"pointX":0.5,"pointY":0.5}},"layers":[{"animations":[],"layers":[],"texturedRectangle":{"singleTextureOpacity":1,"textXHeight":0.62132399999999999,"textBaseline":0.92678263962268825,"isBackgroundTexture":true,"isVerticalText":false,"textColor":[1,1,1,1],"textureType":6},"initialState":{"affineTransform":[1,0,0,1,0,0],"masksToBounds":false,"rotation":0,"scale":1,"position":{"pointX":350.6295166015625,"pointY":43.439899444580078},"width":619,"sublayerTransform":[1,0,0,0,0,1,0,0,0,0,1,0,0,0,0,1],"contentsRect":{"y":0,"x":0,"width":1,"height":1},"opacity":1,"edgeAntialiasingMask":0,"height":50,"hidden":true,"anchorPoint":{"pointX":0.56159837565630044,"pointY":0.38882118225097656}},"texture":"92685EF305F612428C44D7A698BF32EC"}]},{"animations":[],"initialState":{"affineTransform":[1,0,0,1,0,0],"masksToBounds":false,"rotation":0,"scale":1,"position":{"pointX":1394.142254576087,"pointY":579.25571140942316},"width":459.007653683424,"sublayerTransform":[1,0,0,0,0,1,0,0,0,0,1,0,0,0,0,1],"contentsRect":{"y":0,"x":0,"width":1,"height":1},"opacity":1,"edgeAntialiasingMask":251658240,"height":470.7337128579087,"hidden":false,"anchorPoint":{"pointX":0.5,"pointY":0.5}},"layers":[{"animations":[],"layers":[],"texturedRectangle":{"singleTextureOpacity":1,"textXHeight":0,"shapePath":{"lineWidth":1,"flatness":0.59999999999999998,"lineCapStyle":0,"elements":[{"type":"MoveToPoint","points":[[225.37542146444321,1.88885498046875]]},{"type":"AddLine","points":[[225.37542146444321,53.064457908272743]]},{"type":"AddCurve","points":[[131.84916528506437,53.923918152016995],[53.198377573366088,116.96195098055614],[28.738510608673096,202.8408087939024]]},{"type":"AddLine","points":[[99.311643093824387,235.42543224990368]]},{"type":"AddCurve","points":[[110.48849557626454,175.63102644385799],[162.55486769888739,130.2387381321314],[225.37542146444321,129.32376849651337]]},{"type":"AddLine","points":[[225.37542146444321,176.02301844954491]]},{"type":"AddLine","points":[[343.57533650100231,88.955936715006828]]},{"type":"AddLine","points":[[225.37542146444321,1.88885498046875]]},{"type":"CloseSubpath"},{"type":"MoveToPoint","points":[[377.45044009387493,115.45110702514648]]},{"type":"AddLine","points":[[315.91066856682301,162.02937446534634]]},{"type":"AddCurve","points":[[358.27971336575865,199.74494426754973],[372.30919526879734,262.23808320040553],[346.64022682607174,315.63683825731277]]},{"type":"AddLine","points":[[304.86093239486217,294.78751854598522]]},{"type":"AddLine","points":[[329.98496755957603,439.40194888412952]]},{"type":"AddLine","points":[[460.646081417799,372.4986192882061]]},{"type":"AddLine","points":[[414.87436406314373,349.67325186729431]]},{"type":"AddCurve","points":[[453.95270026598882,269.48669610910292],[436.35817246725492,176.15788323313609],[377.45044009387493,115.45110702514648]]},{"type":"CloseSubpath"},{"type":"MoveToPoint","points":[[22.286109924316406,244.5394482165575]]},{"type":"AddLine","points":[[1.638427734375,389.92010113596916]]},{"type":"AddLine","points":[[46.684250012040138,365.64294356107712]]},{"type":"AddCurve","points":[[95.199852333011222,453.85888657957548],[199.00412826827232,492.77851199898578],[291.63351099193096,462.42895382642746]]},{"type":"AddLine","points":[[277.84150452911854,386.25029824674129]]},{"type":"AddCurve","points":[[217.31669436948141,411.65855567548715],[146.36032260112916,387.84059604968934],[113.86987213790417,329.50949972867966]]},{"type":"AddLine","points":[[154.96359899640083,307.410027384758]]},{"type":"AddLine","points":[[22.286109924316406,244.5394482165575]]},{"type":"CloseSubpath"},{"type":"MoveToPoint","points":[[22.286109924316406,244.5394482165575]]}],"windingRule":0,"lineJoinStyle":0,"miterLimit":10},"isBackgroundTexture":true,"textBaseline":0,"isVerticalText":false,"textureType":5},"initialState":{"affineTransform":[1,0,0,1,0,0],"masksToBounds":false,"rotation":0,"scale":1,"position":{"pointX":229.50382995605469,"pointY":235.36685180664062},"width":462,"sublayerTransform":[1,0,0,0,0,1,0,0,0,0,1,0,0,0,0,1],"contentsRect":{"y":0,"x":0,"width":1,"height":1},"opacity":1,"edgeAntialiasingMask":0,"height":474,"hidden":false,"anchorPoint":{"pointX":0.50030791707885214,"pointY":0.50053946579558939}},"texture":"95BBD3B069FF32CAA2226F972BE9CC09"}]}]}}]}